cobrseo/__init__.py
cobrseo/api/RestClient.py
cobrseo/api/__init__.py
cobrseo/api/dataforseo_labs.py
cobrseo/api/dataforseo_organic.py
cobrseo/crawler/__init__.py
cobrseo/crawler/crawler3k.py
cobrseo/json/__init__.py
cobrseo/json/labs_processing.py
cobrseo/json/serp_processing.py
cobrseo/nlp/__init__.py
cobrseo/nlp/keyword_extraction.py
cobrseo/nlp/parent_keyword.py
cobrseo-0.0.7.dist-info/METADATA
cobrseo-0.0.7.dist-info/WHEEL
cobrseo-0.0.7.dist-info/top_level.txt
cobrseo-0.0.7.dist-info/RECORD
